[
    {
        "id": "9ef19c7390084027a70f8db8662a7330",
        "name": "example1",
        "url": "us.vhserver.xyz"
    },
    {
        "id": "9ef19c7390084027a70f8db8662a7331",
        "name": "example2",
        "url": "f-600145068186.southamerica-east1.run.app"
    },
    {
        "id": "9ef19c7390084027a70f8db8662a7332",
        "name": "example3",
        "url": "m.facebook.com"
    },
    {
        "id": "9ef19c7390084027a70f8db8662a7333",
        "name": "example4",
        "url": "google.com"
    }
]
